outlier_python/outlierRemoval.py
101703312_outlierRemoval-1.0.0.dist-info/LICENSE.txt
101703312_outlierRemoval-1.0.0.dist-info/METADATA
101703312_outlierRemoval-1.0.0.dist-info/WHEEL
101703312_outlierRemoval-1.0.0.dist-info/entry_points.txt
101703312_outlierRemoval-1.0.0.dist-info/top_level.txt
101703312_outlierRemoval-1.0.0.dist-info/RECORD
