Metadata-Version: 2.1
Name: 101703312-outlierRemoval
Version: 1.0.0
Summary: A python package for removing outliers from a dataset using InterQuartile Range (IQR)
Home-page: UNKNOWN
Author: Lovish Jindal
Author-email: ljindal1_be17@thapar.edu
License: UNKNOWN
Platform: UNKNOWN
Classifier: Programming Language :: Python :: 3
Classifier: License :: OSI Approved :: MIT License
Classifier: Operating System :: OS Independent
Requires-Python: >=3.6
Requires-Dist: requests
